main.py
xguide-0.0.1.dist-info/METADATA
xguide-0.0.1.dist-info/WHEEL
xguide-0.0.1.dist-info/top_level.txt
xguide-0.0.1.dist-info/RECORD
