Metadata-Version: 2.4
Name: xguide
Version: 0.0.1
Summary: Design of Experiments and Optimization Tool
Requires-Python: >=3.10
